<?xml version="1.0" encoding="UTF-8"?>
<jcr:root xmlns:sling="http://sling.apache.org/jcr/sling/1.0" xmlns:cq="http://www.day.com/jcr/cq/1.0" xmlns:jcr="http://www.jcp.org/jcr/1.0" xmlns:nt="http://www.jcp.org/jcr/nt/1.0"
    jcr:primaryType="nt:unstructured"
    jcr:title="Event Date And Location"
    sling:resourceType="cq/gui/components/authoring/dialog">
    <content
        jcr:primaryType="nt:unstructured"
        sling:resourceType="granite/ui/components/foundation/container">
        <layout
            jcr:primaryType="nt:unstructured"
            sling:resourceType="granite/ui/components/foundation/layouts/tabs"
            type="nav"/>
        <items jcr:primaryType="nt:unstructured">
            <eventinfo
                jcr:primaryType="nt:unstructured"
                jcr:title="Event Date And Location"
                sling:resourceType="granite/ui/components/foundation/section">
                <layout
                    jcr:primaryType="nt:unstructured"
                    sling:resourceType="granite/ui/components/foundation/layouts/fixedcolumns"
                    margin="{Boolean}false"/>
                <items jcr:primaryType="nt:unstructured">
                    <column
                        jcr:primaryType="nt:unstructured"
                        sling:resourceType="granite/ui/components/foundation/container">
                        <items jcr:primaryType="nt:unstructured">
                            <mapLinkLabel
                                jcr:primaryType="nt:unstructured"
                                sling:resourceType="granite/ui/components/coral/foundation/form/textfield"
                                fieldLabel="Map Link CTA Label"
                                name="./mapLinkLabel"
                                required="{Boolean}true"/>
                            <dateTimeLabel
                                jcr:primaryType="nt:unstructured"
                                sling:resourceType="granite/ui/components/coral/foundation/form/textfield"
                                fieldLabel="Date And Time Label"
                                name="./dateTimeLabel"
                                required="{Boolean}true"/>
                            <locationNameLabel
                                jcr:primaryType="nt:unstructured"
                                sling:resourceType="granite/ui/components/coral/foundation/form/textfield"
                                fieldLabel="Location Name Label"
                                name="./locationNameLabel"
                                required="{Boolean}true"/>
                        </items>
                    </column>
                </items>
            </eventinfo>
        </items>
    </content>
</jcr:root>
