<?xml version="1.0" encoding="UTF-8"?>
<jcr:root xmlns:sling="http://sling.apache.org/jcr/sling/1.0" xmlns:cq="http://www.day.com/jcr/cq/1.0" xmlns:jcr="http://www.jcp.org/jcr/1.0" 
xmlns:nt="http://www.jcp.org/jcr/nt/1.0" xmlns:granite="http://www.adobe.com/jcr/granite/1.0"
    jcr:primaryType="nt:unstructured"
    jcr:title="Consent Request Gating"
    sling:resourceType="cq/gui/components/authoring/dialog">
    <content
        jcr:primaryType="nt:unstructured"
        sling:resourceType="granite/ui/components/foundation/container">
        <layout
            jcr:primaryType="nt:unstructured"
            sling:resourceType="granite/ui/components/foundation/layouts/tabs"
            type="nav"/>
        <items jcr:primaryType="nt:unstructured">
            <generalTab jcr:primaryType="nt:unstructured"
                jcr:title="General"
                sling:resourceType="granite/ui/components/foundation/section">
                <layout jcr:primaryType="nt:unstructured"
                    sling:resourceType="granite/ui/components/foundation/layouts/fixedcolumns"/>
                <items jcr:primaryType="nt:unstructured">
                    <step1fields
                        jcr:primaryType="nt:unstructured"
                        sling:resourceType="granite/ui/components/foundation/include"
                        path="edc/components/content/premium/consentrequestgating/cq:dialog/general/content"/>
                </items>
            </generalTab>
            <requiredTab jcr:primaryType="nt:unstructured"
                jcr:title="Consent Required"
                sling:resourceType="granite/ui/components/foundation/section">
                <layout jcr:primaryType="nt:unstructured"
                    sling:resourceType="granite/ui/components/foundation/layouts/fixedcolumns"/>
                <items jcr:primaryType="nt:unstructured">
                    <step1fields
                        jcr:primaryType="nt:unstructured"
                        sling:resourceType="granite/ui/components/foundation/include"
                        path="edc/components/content/premium/consentrequestgating/cq:dialog/required/content"/>
                </items>
            </requiredTab>
            <providedTab jcr:primaryType="nt:unstructured"
                jcr:title="Consent Provided"
                sling:resourceType="granite/ui/components/foundation/section">
                <layout jcr:primaryType="nt:unstructured"
                    sling:resourceType="granite/ui/components/foundation/layouts/fixedcolumns"/>
                <items jcr:primaryType="nt:unstructured">
                    <step1fields
                        jcr:primaryType="nt:unstructured"
                        sling:resourceType="granite/ui/components/foundation/include"
                        path="edc/components/content/premium/consentrequestgating/cq:dialog/provided/content"/>
                </items>
            </providedTab>
            <modalTab jcr:primaryType="nt:unstructured"
                jcr:title="Consent Modal"
                sling:resourceType="granite/ui/components/foundation/section">
                <layout jcr:primaryType="nt:unstructured"
                    sling:resourceType="granite/ui/components/foundation/layouts/fixedcolumns"/>
                <items jcr:primaryType="nt:unstructured">
                    <step1fields
                        jcr:primaryType="nt:unstructured"
                        sling:resourceType="granite/ui/components/foundation/include"
                        path="edc/components/content/premium/consentrequestgating/cq:dialog/modal/content"/>
                </items>
            </modalTab>
        </items>
    </content>
</jcr:root>